pyclm/logging/__about__.py
pyclm/logging/__init__.py
python_yandex_cloud_logging-0.1.0.data/data/COPYRIGHT
python_yandex_cloud_logging-0.1.0.data/data/LICENSE
python_yandex_cloud_logging-0.1.0.dist-info/LICENSE
python_yandex_cloud_logging-0.1.0.dist-info/METADATA
python_yandex_cloud_logging-0.1.0.dist-info/WHEEL
python_yandex_cloud_logging-0.1.0.dist-info/top_level.txt
python_yandex_cloud_logging-0.1.0.dist-info/RECORD
